colossal/__init__.py
colossal/examples/__init__.py
colossal/examples/dict_macro.py
colossal/examples/forloop.py
colossal/examples/ifelse.py
colossal/jinja_encoding.py
colossal/macros/__init__.py
colossal/macros/dict_macro.py
colossal/macros/registry.py
colossal/macros_encoding.py
colossal/register_global.py
colossal-0.1.1.dist-info/WHEEL
colossal-0.1.1.dist-info/METADATA
colossal-0.1.1.dist-info/RECORD
