Metadata-Version: 2.1
Name: colossal
Version: 0.1.1
Summary: 
Author: d1618033
Author-email: d1618033@gmail.com
Requires-Python: >=3.6,<4.0
Classifier: Programming Language :: Python :: 3
Classifier: Programming Language :: Python :: 3.6
Classifier: Programming Language :: Python :: 3.7
Classifier: Programming Language :: Python :: 3.8
Requires-Dist: astor (>=0.8.1,<0.9.0)
Requires-Dist: jinja2 (>=2.11.1,<3.0.0)
